shiny_adaptive_filter/__about__.py
shiny_adaptive_filter/__init__.py
shiny_adaptive_filter/adaptive_filter.py
shiny_adaptive_filter/adaptive_filter_module.py
shiny_adaptive_filter/helpers.py
shiny_adaptive_filter-0.0.1.9004.dist-info/METADATA
shiny_adaptive_filter-0.0.1.9004.dist-info/WHEEL
shiny_adaptive_filter-0.0.1.9004.dist-info/licenses/LICENSE.txt
shiny_adaptive_filter-0.0.1.9004.dist-info/RECORD
